<?xml version="1.0" encoding="UTF-8"?>
<database defaultPhpNamingMethod="underscore" heavyIndexing="false" name="propel" defaultIdMethod="native" package="lib.model"><table skipSql="false" abstract="false" name="computer"><column lazyLoad="false" name="id" type="integer" required="true" primaryKey="true" autoIncrement="true"/><column primaryKey="false" required="false" autoIncrement="false" lazyLoad="false" name="name" type="varchar" size="255"/><column primaryKey="false" required="false" autoIncrement="false" lazyLoad="false" name="mac" type="varchar" size="255"/><column primaryKey="false" required="false" autoIncrement="false" lazyLoad="false" name="groups" type="integer" default="0"/><column primaryKey="false" required="false" autoIncrement="false" lazyLoad="false" name="hw" type="longvarchar"/></table><table skipSql="false" abstract="false" name="partition"><column lazyLoad="false" name="id" type="integer" required="true" primaryKey="true" autoIncrement="true"/><column primaryKey="false" required="false" autoIncrement="false" lazyLoad="false" name="size" type="integer" default="0"/><column primaryKey="false" required="false" autoIncrement="false" lazyLoad="false" name="bootable" type="boolean"/><column primaryKey="false" required="false" autoIncrement="false" lazyLoad="false" name="start" type="integer" default="0"/><column primaryKey="false" required="false" autoIncrement="false" lazyLoad="false" name="end" type="integer" default="0"/><column primaryKey="false" required="false" autoIncrement="false" lazyLoad="false" name="cyls" type="integer" default="0"/><column primaryKey="false" required="false" autoIncrement="false" lazyLoad="false" name="blocks" type="integer" default="0"/><column primaryKey="false" required="false" autoIncrement="false" lazyLoad="false" name="device" type="varchar" size="255"/></table><table skipSql="false" abstract="false" name="image"><column lazyLoad="false" name="id" type="integer" required="true" primaryKey="true" autoIncrement="true"/><column primaryKey="false" required="false" autoIncrement="false" lazyLoad="false" name="name" type="varchar" size="255"/></table></database>
